{"createdAt":"2025-05-12T18:29:19.116Z","updatedAt":"2025-07-10T17:13:51.940Z","id":"DYKMTVuYSCHogX7l","name":"Cognito","active":false,"isArchived":false,"nodes":[{"parameters":{"inputSource":"passthrough"},"type":"n8n-nodes-base.executeWorkflowTrigger","typeVersion":1.1,"position":[-220,-40],"id":"94369546-d3c6-4e4b-abb9-600e23042e8a","name":"When Executed by Another Workflow"},{"parameters":{"method":"POST","url":"https://votorantimprd-tmob.auth.sa-east-1.amazoncognito.com/token","sendHeaders":true,"headerParameters":{"parameters":[{"name":"User-Agent","value":"insomnia/8.6.1"},{"name":"Cookie","value":"XSRF-TOKEN=3b4e457f-9db1-4959-b9cb-2ea6a71e2087"},{"name":"cookie","value":"XSRF-TOKEN=3b4e457f-9db1-4959-b9cb-2ea6a71e2087;"}]},"sendBody":true,"contentType":"form-urlencoded","bodyParameters":{"parameters":[{"name":"client_id","value":"4nc7i13buc1vrslh3tuo768c6d"},{"name":"client_secret","value":"19p07i1mofgqdur8s8oj4ns4k6dq8a46m1ffa7e462glh0075irn"},{"name":"grant_type","value":"client_credentials"},{"name":"scope","value":"SalesNetwork/default"}]},"options":{"redirect":{"redirect":{}}}},"type":"n8n-nodes-base.httpRequest","typeVersion":4.2,"position":[-20,-40],"id":"cdab9e2d-888b-47d8-950c-c1b8027d3540","name":"HTTP Request"},{"parameters":{"assignments":{"assignments":[{"id":"3627d0d3-8fb1-4874-ba92-910de4b42489","name":"token","value":"={{ $json.access_token }}","type":"string"}]},"options":{}},"type":"n8n-nodes-base.set","typeVersion":3.4,"position":[200,-40],"id":"1f1e908f-423e-4f53-ab93-6de0e211276e","name":"Token"}],"connections":{"HTTP Request":{"main":[[{"node":"Token","type":"main","index":0}]]},"When Executed by Another Workflow":{"main":[[{"node":"HTTP Request","type":"main","index":0}]]},"Token":{"main":[[]]}},"settings":{"executionOrder":"v1"},"staticData":null,"meta":null,"pinData":{"When Executed by Another Workflow":[{"json":{"query":"start"}}]},"versionId":"6dbe4bdd-bbd3-4e63-85ac-41feb4887b49","triggerCount":0,"tags":[]}